methodic_cache/__init__.py
methodic_cache/_cache.py
methodic_cache/_exceptions.py
methodic_cache/_wrappers.py
methodic_cache/py.typed
methodic_cache-0.3.1.dist-info/LICENSE
methodic_cache-0.3.1.dist-info/WHEEL
methodic_cache-0.3.1.dist-info/METADATA
methodic_cache-0.3.1.dist-info/RECORD
